se/__init__.py
se/about.py
se/add_to_queue.py
se/admin.py
se/analytics.py
se/apps.py
se/archive.py
se/atom.py
se/browser.py
se/browser_chromium.py
se/browser_firefox.py
se/browser_request.py
se/browser_request_hack.py
se/browser_selenium.py
se/builtin.py
se/collection.py
se/cookie.py
se/cookies_import.py
se/crawl_policy_backup.py
se/crawl_queue.py
se/crawlers.py
se/csv.py
se/document.py
se/document_meta.py
se/domain.py
se/download.py
se/excluded_urls_import.py
se/favicon.py
se/history.py
se/html.py
se/html_asset.py
se/html_cache.py
se/html_snapshot.py
se/login.py
se/mime_plugin.py
se/models.py
se/move_to_collection.py
se/online.py
se/opensearch.py
se/page.py
se/profile.py
se/resources.py
se/rest_api.py
se/rest_permissions.py
se/screenshot.py
se/search.py
se/search_form.py
se/search_redirect.py
se/tag.py
se/tag_field.py
se/tags.py
se/tags_list.py
se/test_add_to_queue.py
se/test_admin.py
se/test_archive.py
se/test_atom.py
se/test_browser.py
se/test_collection.py
se/test_commands.py
se/test_cookie.py
se/test_cookies_import.py
se/test_crawl.py
se/test_crawl_queue.py
se/test_csv.py
se/test_document.py
se/test_document_meta.py
se/test_func_document_meta.py
se/test_functionals.py
se/test_html_cache.py
se/test_html_snapshot.py
se/test_migration_collection.py
se/test_mime_plugin.py
se/test_misc.py
se/test_mock.py
se/test_move_to_collection.py
se/test_parser.py
se/test_redirect.py
se/test_requests.py
se/test_rest_api.py
se/test_rest_permissions.py
se/test_search.py
se/test_tag.py
se/test_url.py
se/test_views.py
se/test_views_mixin.py
se/test_webhook.py
se/url.py
se/utils.py
se/views.py
se/webhook.py
se/words.py
se/www.py
se/deps/fake-useragent/src/fake_useragent/__init__.py
se/deps/fake-useragent/src/fake_useragent/errors.py
se/deps/fake-useragent/src/fake_useragent/fake.py
se/deps/fake-useragent/src/fake_useragent/get_version.py
se/deps/fake-useragent/src/fake_useragent/log.py
se/deps/fake-useragent/src/fake_useragent/py.typed
sosse-1.14.2.dist-info/licenses/LICENSE
sosse-1.14.2.dist-info/METADATA
sosse-1.14.2.dist-info/WHEEL
sosse-1.14.2.dist-info/entry_points.txt
sosse-1.14.2.dist-info/top_level.txt
sosse-1.14.2.dist-info/RECORD
