Metadata-Version: 2.4
Name: Sosse
Version: 1.14.2
Summary: Open-source, enterprise-grade web search & archiving.
Author-email: Laurent Defert <laurent_defert@yahoo.fr>
License-Expression: AGPL-3.0-only
Project-URL: homepage, https://sosse.io
Project-URL: source, https://gitlab.com/biolds1/sosse
Project-URL: changelog, https://gitlab.com/biolds1/sosse/-/blob/stable/CHANGELOG.md?ref_type=heads
Project-URL: documentation, https://sosse.readthedocs.io/en/stable/introduction.html
Project-URL: issues, https://github.com/biolds/sosse/issues
Project-URL: funding, https://sosse.io/fr/contact/
Keywords: search engine,crawler,scraping
Classifier: Framework :: Django
Classifier: Programming Language :: Python :: 3
Requires-Python: >=3.11
License-File: LICENSE
Requires-Dist: bs4
Requires-Dist: cssutils
Requires-Dist: defusedxml
Requires-Dist: django<4.3
Requires-Dist: django-filter
Requires-Dist: django-treebeard
Requires-Dist: django-uwsgi
Requires-Dist: djangorestframework
Requires-Dist: drf-spectacular
Requires-Dist: feedparser
Requires-Dist: html5lib
Requires-Dist: langdetect
Requires-Dist: lxml
Requires-Dist: markdown
Requires-Dist: pillow
Requires-Dist: psutil
Requires-Dist: psycopg2-binary
Requires-Dist: publicsuffix2
Requires-Dist: python-magic
Requires-Dist: pytz
Requires-Dist: requests
Requires-Dist: selenium<4.25
Dynamic: license-file
